{
  "project_info": {
    "project_number": "640814012790",
    "firebase_url": " https://smallshopfirebase-default-rtdb.asia-southeast1.firebasedatabase.app",
    "project_id": "smallshopfirebase",
    "storage_bucket": "smallshopfirebase.appspot.com"
  },
  "client": [
    {
      "client_info": {
        "mobilesdk_app_id": "1:640814012790:android:33ad97380ab5036f2d4257",
        "android_client_info": {
          "package_name": "com.example.store_small_bloc"
        }
      },
      "oauth_client": [
        {
          "client_id": "640814012790-faronulc4brhofli7l4lcs3iemqarsue.apps.googleusercontent.com",
          "client_type": 3
        }
      ],
      "api_key": [
        {
          "current_key": "AIzaSyCMbTtllNtw1qsISh0PQHiOGkMUa_wC2vY"
        }
      ],
      "services": {
        "appinvite_service": {
          "other_platform_oauth_client": [
            {
              "client_id": "640814012790-faronulc4brhofli7l4lcs3iemqarsue.apps.googleusercontent.com",
              "client_type": 3
            }
          ]
        }
      }
    }
  ],
  "configuration_version": "1"
}